<?xml version="1.0" encoding="utf-8" ?>
<Defs>
	<!--	<ThingDef ParentName="BuildingBase">
		<defName>AC_GeneCentrifuge</defName>
		<label>gene centrifuge</label>
		<description>text.todo</description>
		<passability>PassThroughOnly</passability>
		<fillPercent>0.4</fillPercent>
		<pathCost>14</pathCost>
		<rotatable>false</rotatable>
		<graphicData>
			<texPath>Things/Building/Misc/GeneCentrifuge</texPath>
			<graphicClass>Graphic_Single</graphicClass>
			<drawSize>(3, 3)</drawSize>
			<shadowData>
				<volume>(1.5, 0.4, 1.5)</volume>
			</shadowData>
		</graphicData>
		<size>(3, 3)</size>
		<canOverlapZones>false</canOverlapZones>
		<defaultPlacingRot>North</defaultPlacingRot>
		<designationCategory>Biotech</designationCategory>
		<uiOrder>2100</uiOrder>
		<statBases>
			<MaxHitPoints>350</MaxHitPoints>
			<WorkToBuild>9000</WorkToBuild>
			<Mass>85</Mass>
			<Flammability>0.5</Flammability>
			<GeneticComplexityIncrease>2</GeneticComplexityIncrease>
		</statBases>
		<costList>
			<Steel>100</Steel>
			<Plasteel>25</Plasteel>
			<ComponentIndustrial>2</ComponentIndustrial>
		</costList>
		<constructionSkillPrerequisite>8</constructionSkillPrerequisite>
		<building>
			<buildingTags>
				<li>Biotech</li>
			</buildingTags>
		</building>
		<placeWorkers>
			<li>PlaceWorker_ShowFacilitiesConnections</li>
		</placeWorkers>
		<drawPlaceWorkersWhileSelected>true</drawPlaceWorkersWhileSelected>
		<comps>
			<li Class="CompProperties_Power">
				<compClass>CompPowerTrader</compClass>
				<basePowerConsumption>50</basePowerConsumption>
			</li>
			<li Class="CompProperties_Flickable"/>
			<li Class="CompProperties_Facility">
				<maxSimultaneous>100</maxSimultaneous>
				<maxDistance>12.9</maxDistance>
			</li>
		</comps>
	</ThingDef>-->
	<!-- ================================ Gene Vault ====================== -->
	<ThingDef ParentName="GeneBuildingBase">
		<defName>AC_GeneVault</defName>
		<label>gene vault</label>
		<description>text.todo</description>
		<graphicData>
			<texPath>Things/Building/Misc/GeneVault/GeneVault</texPath>
			<graphicClass>Graphic_Multi</graphicClass>
			<drawSize>(5, 3)</drawSize>
		</graphicData>
		<size>(5, 3)</size>
		<descriptionHyperlinks>
			<ThingDef>Genepack</ThingDef>
			<ThingDef>GeneBank</ThingDef>
			<ThingDef>GeneAssembler</ThingDef>
		</descriptionHyperlinks>
		<passability>PassThroughOnly</passability>
		<castEdgeShadows>true</castEdgeShadows>
		<fillPercent>0.4</fillPercent>
		<pathCost>14</pathCost>
		<tickerType>Rare</tickerType>
		<canOverlapZones>false</canOverlapZones>
		<defaultPlacingRot>South</defaultPlacingRot>
		<designationCategory>Biotech</designationCategory>
		<researchPrerequisites>
			<li>GeneProcessor</li>
		</researchPrerequisites>
		<statBases>
			<MaxHitPoints>800</MaxHitPoints>
			<WorkToBuild>15000</WorkToBuild>
			<Mass>85</Mass>
			<Flammability>0.5</Flammability>
			<GeneticComplexityIncrease>2</GeneticComplexityIncrease>
		</statBases>
		<costList>
			<Steel>200</Steel>
			<Plasteel>50</Plasteel>
			<ComponentIndustrial>4</ComponentIndustrial>
		</costList>
		<constructionSkillPrerequisite>8</constructionSkillPrerequisite>
		<inspectorTabs>
			<li>ITab_ContentsGenepackHolder</li>
		</inspectorTabs>
		<placeWorkers>
			<li>PlaceWorker_ShowFacilitiesConnections</li>
		</placeWorkers>
		<drawPlaceWorkersWhileSelected>true</drawPlaceWorkersWhileSelected>
		<comps>
			<li Class="CompProperties_Power">
				<compClass>CompPowerTrader</compClass>
				<basePowerConsumption>150</basePowerConsumption>
			</li>
			<li Class="CompProperties_GenepackContainer">
				<maxCapacity>16</maxCapacity>
			</li>
			<li Class="CompProperties_Flickable"/>
			<li Class="CompProperties_Facility">
				<maxSimultaneous>100</maxSimultaneous>
				<maxDistance>12.9</maxDistance>
			</li>
			<li Class="CompProperties_Flickable"/>
		</comps>
	</ThingDef>
</Defs>