<?xml version="1.0" encoding="utf-8"?>
<ModMetaData>
	<name>Altered Carbon 2: ReSleeved</name>
	<author>Helixien</author>
	<supportedVersions>
		<li>1.5</li>
		<li>1.4</li>
	</supportedVersions>
	<modVersion>6.0-Sovereign-rev1</modVersion>
	<packageId>hlx.UltratechAlteredCarbon</packageId>
	<description>This module adds ultratech technology, predominantly from “Altered Carbon”, the popular Netflix show and book series by Richard K. Morgan, into Rimworld.</description>
	<url>https://steamcommunity.com/sharedfiles/filedetails/?id=2196278117</url>
	<modDependencies>
		<li>
			<packageId>OskarPotocki.VanillaFactionsExpanded.Core</packageId>
			<displayName>Vanilla Expanded Framework</displayName>
			<downloadUrl>https://github.com/Vanilla-Expanded/VanillaExpandedFramework</downloadUrl>
			<steamWorkshopUrl>https://steamcommunity.com/workshop/filedetails/?id=2023507013</steamWorkshopUrl>
		</li>
	</modDependencies>
	<modDependenciesByVersion>
		<v1.4>
			<li>
				<packageId>OskarPotocki.VanillaFactionsExpanded.Core</packageId>
				<displayName>Vanilla Expanded Framework</displayName>
				<downloadUrl>https://github.com/Vanilla-Expanded/VanillaExpandedFramework</downloadUrl>
				<steamWorkshopUrl>https://steamcommunity.com/workshop/filedetails/?id=2023507013</steamWorkshopUrl>
			</li>
			<li>
				<packageId>Ludeon.RimWorld.Biotech</packageId>
				<displayName>Biotech</displayName>
				<downloadUrl>https://store.steampowered.com/app/1826140/RimWorld__Biotech/</downloadUrl>
			</li>
		</v1.4>
	</modDependenciesByVersion>
	<loadAfter>
		<li>brrainz.harmony</li>
		<li>OskarPotocki.VanillaFactionsExpanded.Core</li>
		<li>VanillaExpanded.VFEA</li>
		<li>OskarPotocki.VFE.Empire</li>
		<li>OskarPotocki.VFE.Pirates</li>
		<li>OskarPotocki.VFE.Vikings</li>
		<li>vanillaracesexpanded.android</li>
	</loadAfter>
</ModMetaData>