<?xml version="1.0" encoding="utf-8" ?>
<Defs>
	<!-- ================================ Special Filters for Neural Stacks====================== -->
	<SpecialThingFilterDef>
		<defName>AC_AllowStacksColonist</defName>
		<label>allow colonist stacks</label>
		<description>Allow the stacks of colonists.</description>
		<parentCategory>AC_BodyPartsUltra</parentCategory>
		<allowedByDefault>true</allowedByDefault>
		<saveKey>allowStacksColonist</saveKey>
		<workerClass>AlteredCarbon.SpecialThingFilterWorker_StacksColonist</workerClass>
	</SpecialThingFilterDef>
	<SpecialThingFilterDef>
		<defName>AC_AllowStacksStranger</defName>
		<label>allow stranger stacks</label>
		<description>Allow the stacks of strangers.</description>
		<parentCategory>AC_BodyPartsUltra</parentCategory>
		<allowedByDefault>true</allowedByDefault>
		<saveKey>allowStacksStranger</saveKey>
		<workerClass>AlteredCarbon.SpecialThingFilterWorker_StacksStranger</workerClass>
	</SpecialThingFilterDef>
	<SpecialThingFilterDef>
		<defName>AC_AllowStacksHostile</defName>
		<label>allow hostile stacks</label>
		<description>Allow the stacks of hostiles and enemies.</description>
		<parentCategory>AC_BodyPartsUltra</parentCategory>
		<allowedByDefault>true</allowedByDefault>
		<saveKey>allowStacksHostile</saveKey>
		<workerClass>AlteredCarbon.SpecialThingFilterWorker_StacksHostile</workerClass>
	</SpecialThingFilterDef>
</Defs>