<?xml version="1.0" encoding="utf-8"?>
<Defs>
	<!-- ================================ Altered Carbon - Research Abstract	====================== -->
	<ResearchProjectDef Name="AC_ResearchBase" Abstract="True">
		<techLevel>Ultra</techLevel>
		<requiredResearchBuilding>HiTechResearchBench</requiredResearchBuilding>
		<requiredResearchFacilities>
			<li>MultiAnalyzer</li>
		</requiredResearchFacilities>
	</ResearchProjectDef>
	<!-- ================================ Sleeve Gestating ====================== -->
	<ResearchProjectDef ParentName="AC_ResearchBase">
		<defName>AC_SleeveGestation</defName>
		<label>sleeve gestation</label>
		<description>Develop biotechnologies to create highly customizable synthetic bodies called sleeves for usage with persona stacks.</description>
		<baseCost>6000</baseCost>
		<researchViewX>12.00</researchViewX>
		<researchViewY>2.90</researchViewY>
		<prerequisites>
			<li>MicroelectronicsBasics</li>
		</prerequisites>
	</ResearchProjectDef>
</Defs>